ewallet/__init__.py
ewallet/auth.py
ewallet/config.py
ewallet/connect.py
ewallet/models.py
ewallet/services.py
ewallet/utils.py
python_sdk_ewallet-0.0.2.dist-info/LICENSE
python_sdk_ewallet-0.0.2.dist-info/METADATA
python_sdk_ewallet-0.0.2.dist-info/WHEEL
python_sdk_ewallet-0.0.2.dist-info/top_level.txt
python_sdk_ewallet-0.0.2.dist-info/RECORD
