Metadata-Version: 2.1
Name: python-sdk-ewallet
Version: 0.0.2
Summary: Python SDK for LianLian Global e-wallet program
Home-page: https://developer.lianlianglobal.com/docs/e-wallet-openapi
Author: yangdm002
Author-email: yangdm002@lianlianpay.com
Classifier: Programming Language :: Python :: 3
Classifier: License :: OSI Approved :: MIT License
Classifier: Operating System :: OS Independent
Requires-Python: >=3.6
License-File: LICENSE
